flask_cdn.py
setup.cfg
setup.py
Flask_CDN_NG.egg-info/PKG-INFO
Flask_CDN_NG.egg-info/SOURCES.txt
Flask_CDN_NG.egg-info/dependency_links.txt
Flask_CDN_NG.egg-info/not-zip-safe
Flask_CDN_NG.egg-info/requires.txt
Flask_CDN_NG.egg-info/top_level.txt