Metadata-Version: 1.1
Name: Flask-CDN-NG
Version: 1.3.0
Summary: Serve the static files in your Flask app from a CDN.
Home-page: https://github.com/s-m-i-t-a/flask-cdn-ng
Author: Jindřich K. Smitka
Author-email: smitka.j@gmail.com
License: MIT
Platform: any
Classifier: Environment :: Web Environment
Classifier: Intended Audience :: Developers
Classifier: License :: OSI Approved :: MIT License
Classifier: Operating System :: OS Independent
Classifier: Programming Language :: Python
Classifier: Topic :: Internet :: WWW/HTTP :: Dynamic Content
Classifier: Topic :: Software Development :: Libraries :: Python Modules
